README.md
setup.py
connectorcomet/__init__.py
connectorcomet/connector.py
connectorcomet.egg-info/PKG-INFO
connectorcomet.egg-info/SOURCES.txt
connectorcomet.egg-info/dependency_links.txt
connectorcomet.egg-info/requires.txt
connectorcomet.egg-info/top_level.txt