Metadata-Version: 2.1
Name: connectorcomet
Version: 0.1
Summary: A Python package to connect to the Comet API
Home-page: UNKNOWN
Author: Lucas Bracamonte
Author-email: ing.lucasbracamonte@gmail.com
License: UNKNOWN
Platform: UNKNOWN
